series_tiempo_ar/__init__.py
series_tiempo_ar/core.py
series_tiempo_ar/custom_exceptions.py
series_tiempo_ar/helpers.py
series_tiempo_ar/paths.py
series_tiempo_ar/search.py
series_tiempo_ar/time_series_validator.py
series_tiempo_ar/readers/csv_reader.py
series_tiempo_ar/readers/readers.py
series_tiempo_ar/readers/text_file_reader.py
series_tiempo_ar/schemas/accrualPeriodicity.json
series_tiempo_ar/schemas/catalog.json
series_tiempo_ar/schemas/dataset.json
series_tiempo_ar/schemas/distribution.json
series_tiempo_ar/schemas/field.json
series_tiempo_ar/schemas/mixed-types.json
series_tiempo_ar/schemas/required_fields_schema.json
series_tiempo_ar/schemas/superThemeTaxonomy.json
series_tiempo_ar/schemas/theme.json
series_tiempo_ar/utils/url_validator.py
series_tiempo_ar/validations/__init__.py
series_tiempo_ar/validations/csv_validations.py
series_tiempo_ar/validations/validators.py
series_tiempo_ar/validations/xlsx_validations.py
series_tiempo_ar-0.4.0.dist-info/LICENSE
series_tiempo_ar-0.4.0.dist-info/METADATA
series_tiempo_ar-0.4.0.dist-info/WHEEL
series_tiempo_ar-0.4.0.dist-info/top_level.txt
series_tiempo_ar-0.4.0.dist-info/RECORD
