Metadata-Version: 2.1
Name: series-tiempo-ar
Version: 0.4.0
Summary: Módulos para extraer, analizar y compilar series de tiempo documentadas en catálogos de datos abiertos basados en el perfil de metadatos del Paquete de Apertura de Datos.
Home-page: https://github.com/datosgobar/series-tiempo-ar
Author: Datos Argentina
Author-email: datos@modernizacion.gob.ar
License: MIT license
Keywords: series_tiempo_ar
Platform: UNKNOWN
Classifier: Development Status :: 2 - Pre-Alpha
Classifier: Intended Audience :: Developers
Classifier: License :: OSI Approved :: MIT License
Classifier: Natural Language :: English
Classifier: Programming Language :: Python :: 3
Classifier: Programming Language :: Python :: 3.6
Requires-Dist: arrow
Requires-Dist: pandas
Requires-Dist: python-dateutil
Requires-Dist: pydatajson (>=0.4.41)
Requires-Dist: six
